{
 "based_on": "creation",
 "chart_name": "HP Product Purchase",
 "chart_type": "Sum",
 "creation": "2024-05-18 13:03:10.605728",
 "docstatus": 0,
 "doctype": "Dashboard Chart",
 "document_type": "Purchase Invoice Item",
 "dynamic_filters_json": "[]",
 "filters_json": "[[\"Purchase Invoice Item\",\"item_group\",\"like\",\"%HP%\",false]]",
 "group_by_type": "Count",
 "idx": 0,
 "is_public": 0,
 "is_standard": 1,
 "last_synced_on": "2024-05-18 12:50:52.657060",
 "modified": "2024-05-18 13:03:18.858978",
 "modified_by": "mushylimdi@gmail.com",
 "module": "Smb Report",
 "name": "HP Product Purchase",
 "number_of_groups": 0,
 "owner": "mushylimdi@gmail.com",
 "parent_document_type": "Purchase Invoice",
 "roles": [],
 "source": "",
 "time_interval": "Monthly",
 "timeseries": 1,
 "timespan": "Last Year",
 "type": "Bar",
 "use_report_chart": 0,
 "value_based_on": "net_amount",
 "y_axis": []
}